ObjectDelegator/__init__.py
ObjectDelegator/delegator.py
ObjectDelegator-1.1.dist-info/LICENSE
ObjectDelegator-1.1.dist-info/METADATA
ObjectDelegator-1.1.dist-info/WHEEL
ObjectDelegator-1.1.dist-info/top_level.txt
ObjectDelegator-1.1.dist-info/RECORD
