Metadata-Version: 2.1
Name: ObjectDelegator
Version: 1.1
Summary: This minimal yet powerful library allows delegation of an objects: methods, properties, and his own member objects, to an object who owns it. Recursive delegation is also supported.Use the simple API to handle delegations.
Home-page: https://github.com/YairMZ/ObjectDelegator
Author: Yair Mazal
Author-email: mazaly@post.bgu.ac.il
License: GNU General Public License v3.0
Download-URL: https://github.com/YairMZ/ObjectDelegator/archive/v1.1.tar.gz
Keywords: OOP,delegation,composition
Platform: UNKNOWN
Classifier: Programming Language :: Python :: 3
Classifier: License :: OSI Approved :: GNU General Public License v3 (GPLv3)
Classifier: Operating System :: OS Independent
Classifier: Development Status :: 3 - Alpha
Classifier: Topic :: Software Development :: Object Brokering
Requires-Python: >=3.8
